bitbuilder/__init__.py
bitbuilder/_listener.py
bitbuilder/bitbuilder_client.py
bitbuilder/cli.py
bitbuilder/src/__init__.py
bitbuilder/src/listener/__init__.py
bitbuilder/src/listener/cloud_dev_env_listener.py
bitbuilder/src/models/__init__.py
bitbuilder/src/models/workspaces/__init__.py
bitbuilder/src/models/workspaces/command.py
bitbuilder/src/models/workspaces/constants.py
bitbuilder/src/models/workspaces/models.py
bitbuilder/src/models/workspaces/workspace_config.py
bitbuilder/src/models/workspaces/workspace_type.py
bitbuilder_cli-0.1.17.dist-info/entry_points.txt
bitbuilder_cli-0.1.17.dist-info/LICENSE
bitbuilder_cli-0.1.17.dist-info/WHEEL
bitbuilder_cli-0.1.17.dist-info/METADATA
bitbuilder_cli-0.1.17.dist-info/RECORD
